[
  {
    "menu_id": "1014",
    "menu_name": "平台管理",
    "menu_url": null,
    "icon": "navIcon-setup",
    "p_id": null,
    "is_open": "10",
    "open_style":null,
    "menu_level":"10"
  },
  {
    "menu_id": "101401",
    "menu_name": "机构管理",
    "menu_url": "#platform/web_pub/org/org_list/org_list",
    "icon": "",
    "p_id": "1014",
    "is_open": "20",
    "open_style":"10",
    "menu_level":"20"
  },
  {
    "menu_id": "101401",
    "menu_name": "医院管理",
    "menu_url": "#platform/web_pub/hos/hos_list/hos_list",
    "icon": "",
    "p_id": "1014",
    "is_open": "20",
    "open_style":"10",
    "menu_level":"20"
  },
  {
    "menu_id": "101401",
    "menu_name": "科室管理",
    "menu_url": "#platform/web_pub/dep/dep_list/dep_list",
    "icon": "",
    "p_id": "1014",
    "is_open": "20",
    "open_style":"10",
    "menu_level":"20"
  },
  {
    "menu_id": "101401",
    "menu_name": "医生管理",
    "menu_url": "#platform/web_pub/doc/doc_list/doc_list",
    "icon": "",
    "p_id": "1014",
    "is_open": "20",
    "open_style":"10",
    "menu_level":"20"
  },
  {
    "menu_id": "101401",
    "menu_name": "运营人员管理",
    "menu_url": "#platform/web_pub/oper_user/oper_user_list/oper_user_list",
    "icon": "",
    "p_id": "1014",
    "is_open": "20",
    "open_style":"10",
    "menu_level":"20"
  },
  {
    "menu_id": "101401",
    "menu_name": "角色权限管理",
    "menu_url": "#platform/web_pub/role_perm/role_perm_list/role_perm_list",
    "icon": "",
    "p_id": "1014",
    "is_open": "20",
    "open_style":"10",
    "menu_level":"20"
  },
  {
    "menu_id": "101401",
    "menu_name": "系统权限管理",
    "menu_url": "#platform/web_pub/sys_perm/sys_perm_list/sys_perm_list",
    "icon": "",
    "p_id": "1014",
    "is_open": "20",
    "open_style":"10",
    "menu_level":"20"
  },
  {
    "menu_id": "101401",
    "menu_name": "菜单配置",
    "menu_url": "#platform/web_pub/menu/menu_list/menu_list",
    "icon": "",
    "p_id": "1014",
    "is_open": "20",
    "open_style":"10",
    "menu_level":"20"
  }
]